dcs_jupyter/__init__.py
dcs_jupyter/cli.py
dcs_jupyter/kernel.py
dcs_jupyter/py.typed
dcs_jupyter-0.1.4.dist-info/METADATA
dcs_jupyter-0.1.4.dist-info/WHEEL
dcs_jupyter-0.1.4.dist-info/entry_points.txt
dcs_jupyter-0.1.4.dist-info/licenses/LICENSE
dcs_jupyter-0.1.4.dist-info/RECORD
