Metadata-Version: 2.4
Name: dcs-jupyter
Version: 0.1.4
Summary: Jupyter kernel for live connection to DCS (Digital Combat Simulator) scripting environment
Author-email: Sami Ahola <sami.ahola@iki.fi>
Maintainer-email: Sami Ahola <sami.ahola@iki.fi>
License: MIT
License-File: LICENSE
Keywords: dcs,digital-combat-simulator,flight-simulation,jupyter,kernel,lua
Classifier: Development Status :: 4 - Beta
Classifier: Framework :: Jupyter
Classifier: Framework :: Jupyter :: JupyterLab
Classifier: Intended Audience :: Developers
Classifier: Intended Audience :: Science/Research
Classifier: License :: OSI Approved :: MIT License
Classifier: Operating System :: OS Independent
Classifier: Programming Language :: Lua
Classifier: Programming Language :: Python :: 3
Classifier: Programming Language :: Python :: 3.11
Classifier: Programming Language :: Python :: 3.12
Classifier: Programming Language :: Python :: 3.13
Classifier: Topic :: Scientific/Engineering
Classifier: Topic :: Software Development :: Libraries :: Python Modules
Classifier: Topic :: System :: Shells
Requires-Python: >=3.11
Requires-Dist: ipykernel>=6.29.5
Requires-Dist: jupyter-console>=6.6.3
Provides-Extra: lab
Requires-Dist: jldracula>=0.2.0; extra == 'lab'
Requires-Dist: jupyterlab-vim>=4.1.4; extra == 'lab'
Requires-Dist: jupyterlab>=4.2.5; extra == 'lab'
Requires-Dist: rich[jupyter]>=13.9.1; extra == 'lab'
